CHANGES.txt
README.txt
bootstrap.py
buildout.cfg
setup.py
src/zope/__init__.py
src/zope.app.pluggableauth.egg-info/PKG-INFO
src/zope.app.pluggableauth.egg-info/SOURCES.txt
src/zope.app.pluggableauth.egg-info/dependency_links.txt
src/zope.app.pluggableauth.egg-info/namespace_packages.txt
src/zope.app.pluggableauth.egg-info/not-zip-safe
src/zope.app.pluggableauth.egg-info/requires.txt
src/zope.app.pluggableauth.egg-info/top_level.txt
src/zope/app/__init__.py
src/zope/app/pluggableauth/README.txt
src/zope/app/pluggableauth/SETUP.cfg
src/zope/app/pluggableauth/__init__.py
src/zope/app/pluggableauth/configure.zcml
src/zope/app/pluggableauth/interfaces.py
src/zope/app/pluggableauth/zope.app.pluggableauth-configure.zcml
src/zope/app/pluggableauth/browser/__init__.py
src/zope/app/pluggableauth/browser/configure.zcml
src/zope/app/pluggableauth/tests/__init__.py
src/zope/app/pluggableauth/tests/authsetup.py
src/zope/app/pluggableauth/tests/test_pluggableauth.py
